README.md
setup.cfg
setup.py
telegrampy/__init__.py
telegrampy/client.py
telegrampy/conf.py
telegrampy/exceptions.py
telegrampy/utils.py
telegrampy.egg-info/PKG-INFO
telegrampy.egg-info/SOURCES.txt
telegrampy.egg-info/dependency_links.txt
telegrampy.egg-info/not-zip-safe
telegrampy.egg-info/requires.txt
telegrampy.egg-info/top_level.txt