Metadata-Version: 1.0
Name: telegrampy
Version: 0.1.0
Summary: Python client to send notifications through Telegram.
Home-page: https://github.com/pasqualguerrero/telegrampy
Author: Pasqual Guerrero
Author-email: pasqual.guerrero@gmail.com
License: MIT
Platform: UNKNOWN
